flametree/Directory.py
flametree/DiskFileManager.py
flametree/ZipFileManager.py
flametree/__init__.py
flametree/utils.py
flametree/version.py
flametree-0.2.0.dist-info/licenses/LICENCE.txt
tests/test_basics.py
tests/test_third_parties.py
flametree-0.2.0.dist-info/METADATA
flametree-0.2.0.dist-info/WHEEL
flametree-0.2.0.dist-info/top_level.txt
flametree-0.2.0.dist-info/RECORD
